[
  {
    "X_id": "584e9e9e16c08e000fb7e146",
    "createdAt": "2016-12-12 12:57:02",
    "updatedAt": "2018-01-08 12:38:16",
    "name": "Rathaus_Kerpen_KDVZ",
    "exposure": "outdoor",
    "model": "homeWifiFeinstaub",
    "description": "Rathausdach Stadt Kerpen",
    "grouptag": "KDVZ",
    "phenomena": ["Temperatur", "rel. Luftfeuchte", "Luftdruck", "Beleuchtungsstärke", "UV-Intensität", "PM10", "PM2.5"],
    "lastMeasurement": "2018-01-08 12:38:11",
    "lon": 6.691457,
    "lat": 50.872989
  },
  {
    "X_id": "5852edf116c08e000fd20768",
    "createdAt": "2016-12-15 19:24:33",
    "updatedAt": "2018-01-08 12:37:56",
    "name": "K4 Senden",
    "exposure": "outdoor",
    "model": "homeWifiFeinstaub",
    "phenomena": ["Temperatur", "rel. Luftfeuchte", "Luftdruck", "Beleuchtungsstärke", "UV-Intensität", "PM10", "PM2.5"],
    "lastMeasurement": "2018-01-08 12:37:56",
    "lon": 7.490391,
    "lat": 51.857716
  },
  {
    "X_id": "58b4531ee53e0b001251d07b",
    "createdAt": "2017-02-27 16:26:06",
    "updatedAt": "2018-01-08 12:38:04",
    "name": "Alfredstr.",
    "exposure": "outdoor",
    "model": "homeWifiFeinstaub",
    "description": "Standort ist der erste Stock auf dem Balkon.",
    "phenomena": ["Temperatur", "rel. Luftfeuchte", "Luftdruck", "Beleuchtungsstärke", "UV-Intensität", "PM10", "PM2.5"],
    "lastMeasurement": "2018-01-08 12:38:04",
    "lon": 13.489709,
    "lat": 52.512982
  },
  {
    "X_id": "58c89a56c519fa0011881e58",
    "createdAt": "2017-03-15 01:35:18",
    "updatedAt": "2018-01-08 12:38:12",
    "name": "Roland Th.",
    "exposure": "outdoor",
    "model": "homeWifiFeinstaub",
    "description": "Meine Daten werden anhand des Feinstaubsensors ermittelt vom Projekt luftdaten.info.\nMeine Sensoren Sind SDS011 und DHT22 gesteuert von einem NodeMCU ESP8266",
    "grouptag": "Feinstaubsensor",
    "phenomena": ["Temperatur", "rel. Luftfeuchte", "PM10", "PM2.5"],
    "lon": 10.183146,
    "lat": 54.299341,
    "weblink": "https://13th769.de"
  },
  {
    "X_id": "58d00131c877fb00118a494f",
    "createdAt": "2017-03-20 16:20:01",
    "updatedAt": "2018-01-08 12:37:27",
    "name": "Galgenberg",
    "exposure": "outdoor",
    "model": "homeWifiFeinstaub",
    "description": "Temperatur-/Feuchtewerte werden durch Sonneneinstrahlung beeinflusst, da die Station der Sonne ausgesetzt ist und kein ausreichender Strahlungsschutz besteht. Station dient vornehmlich der Messung von Feinstaub",
    "grouptag": "Sensoren Luftdaten.info",
    "phenomena": ["Temperatur", "rel. Luftfeuchte", "PM10", "PM2.5", "Temperatur", "rel. Luftfeuchte"],
    "lastMeasurement": "2017-11-13 13:58:45",
    "lon": 12.104681,
    "lat": 49.006848
  },
  {
    "X_id": "591f578c51d34600116a8ea5",
    "createdAt": "2017-05-19 20:37:32",
    "updatedAt": "2018-01-08 12:38:11",
    "name": "Wetterstation Erpho",
    "exposure": "outdoor",
    "model": "homeWifiFeinstaub",
    "description": "- TESTBETRIEB -",
    "phenomena": ["Temperatur", "rel. Luftfeuchte", "Luftdruck", "Beleuchtungsstärke", "UV-Intensität", "UV-Index", "PM10", "PM2.5", "Windgeschwindigkeit", "Windböen", "Windrichtung", "Niederschlag"],
    "lastMeasurement": "2018-01-08 12:38:11",
    "lon": 7.645218,
    "lat": 51.96422
  },
  {
    "X_id": "59479ed5a4ad5900112d8dec",
    "createdAt": "2017-06-19 09:52:21",
    "updatedAt": "2018-01-08 12:36:53",
    "name": "SDS011LanuvEvaluation",
    "exposure": "outdoor",
    "model": "homeWifiFeinstaub",
    "grouptag": "ifgi",
    "phenomena": ["Temperatur", "rel. Luftfeuchte", "Luftdruck", "Beleuchtungsstärke", "UV-Intensität", "PM10", "PM2.5"],
    "lastMeasurement": "2018-01-08 12:36:53",
    "lon": 7.45741,
    "lat": 51.53689
  },
  {
    "X_id": "594bd2eebe77820011771698",
    "createdAt": "2017-06-22 14:23:42",
    "updatedAt": "2018-01-08 12:37:24",
    "name": "Niederfeld",
    "exposure": "outdoor",
    "model": "homeWifiFeinstaub",
    "phenomena": ["Temperatur", "rel. Luftfeuchte", "Luftdruck", "Beleuchtungsstärke", "UV-Intensität", "PM10", "PM2.5"],
    "lastMeasurement": "2018-01-08 12:37:24",
    "lon": 8.478312,
    "lat": 52.248981
  },
  {
    "X_id": "5956b37594f0520011229583",
    "createdAt": "2017-06-30 20:24:21",
    "updatedAt": "2018-01-08 12:38:20",
    "name": "HX_Windthorststraße",
    "exposure": "outdoor",
    "model": "homeWifiFeinstaub",
    "phenomena": ["Temperatur", "rel. Luftfeuchte", "Luftdruck", "Beleuchtungsstärke", "UV-Intensität", "PM10", "PM2.5"],
    "lastMeasurement": "2018-01-08 12:38:20",
    "lon": 9.35378,
    "lat": 51.805497
  },
  {
    "X_id": "595a887694f052001157633d",
    "createdAt": "2017-07-03 18:09:58",
    "updatedAt": "2018-01-08 12:37:48",
    "name": "Poststraße",
    "exposure": "outdoor",
    "model": "homeWifiFeinstaub",
    "phenomena": ["Temperatur", "rel. Luftfeuchte", "Luftdruck", "Beleuchtungsstärke", "UV-Intensität", "PM10", "PM2.5"],
    "lastMeasurement": "2018-01-08 12:37:48",
    "lon": 8.390411,
    "lat": 51.04798
  },
  {
    "X_id": "595c9b3e94f0520011752694",
    "createdAt": "2017-07-05 07:54:38",
    "updatedAt": "2017-07-11 15:11:13",
    "name": "Ratingenwetter",
    "exposure": "outdoor",
    "model": "homeWifiFeinstaub",
    "description": "Wetterstation Ratingen-Breitscheid",
    "phenomena": ["PM10", "PM2.5"],
    "lastMeasurement": "2018-01-01 03:59:13",
    "lon": 6.873,
    "lat": 51.357
  },
  {
    "X_id": "595e71f994f0520011900177",
    "createdAt": "2017-07-06 17:23:05",
    "updatedAt": "2018-01-08 12:37:47",
    "name": "Schwedler (Erkrath-Unterfeldhaus)",
    "exposure": "outdoor",
    "model": "homeWifiFeinstaub",
    "description": "Die erste senseBox in Erkrath (seit April 2017)! senseBox:home Wifi mit Feinstaubsensor.",
    "phenomena": ["Temperatur", "rel. Luftfeuchte", "Luftdruck", "Beleuchtungsstärke", "UV-Intensität", "PM10", "PM2.5"],
    "lastMeasurement": "2018-01-08 12:37:47",
    "lon": 6.914467,
    "lat": 51.202904
  },
  {
    "X_id": "5961fe1694f0520011c2a3ba",
    "createdAt": "2017-07-09 09:57:42",
    "updatedAt": "2018-01-08 12:38:01",
    "name": "._.",
    "exposure": "outdoor",
    "model": "homeWifiFeinstaub",
    "description": "Witten Innenstadt",
    "phenomena": ["Temperatur", "rel. Luftfeuchte", "Luftdruck", "Beleuchtungsstärke", "UV-Intensität", "PM10", "PM2.5"],
    "lastMeasurement": "2018-01-08 12:38:01",
    "lon": 7.331309,
    "lat": 51.440607
  },
  {
    "X_id": "596914641900bf001101bd2c",
    "createdAt": "2017-07-14 18:58:44",
    "updatedAt": "2018-01-08 12:37:10",
    "name": "Ringelberg01",
    "exposure": "outdoor",
    "model": "homeWifiFeinstaub",
    "grouptag": "Luftdaten",
    "phenomena": ["Luftdruck", "PM10", "PM2.5", "Temperatur", "Luftfeuchte"],
    "lastMeasurement": "2018-01-08 12:37:10",
    "lon": 11.067063,
    "lat": 50.988774
  },
  {
    "X_id": "5991537e7e280a0010421ba7",
    "createdAt": "2017-08-14 07:38:38",
    "updatedAt": "2018-01-08 12:37:33",
    "name": "Staubsensor",
    "exposure": "outdoor",
    "model": "homeWifiFeinstaub",
    "phenomena": ["PM10", "PM2.5", "Temperatur", "rel. Luftfeuchte"],
    "lastMeasurement": "2018-01-08 12:37:33",
    "lon": 11.536652,
    "lat": 48.153313
  },
  {
    "X_id": "59a42c92d67eb50011112c74",
    "createdAt": "2017-08-28 14:45:38",
    "updatedAt": "2018-01-08 12:38:19",
    "name": "Alt-Moabit/Gotzkowskystraße",
    "exposure": "outdoor",
    "model": "homeWifiFeinstaub",
    "description": "Ca. 16m über Straßenlevel, keine direktes Sonnenlicht außer früh morgens und spät abends",
    "phenomena": ["Temperatur", "rel. Luftfeuchte", "Luftdruck", "Beleuchtungsstärke", "UV-Intensität", "PM10", "PM2.5"],
    "lastMeasurement": "2018-01-08 12:38:19",
    "lon": 13.32931,
    "lat": 52.523727
  },
  {
    "X_id": "59b26deed67eb500110ae4e7",
    "createdAt": "2017-09-08 10:16:14",
    "updatedAt": "2018-01-08 12:37:50",
    "name": "Elisenhof Elsdorf",
    "exposure": "outdoor",
    "model": "homeWifiFeinstaub",
    "phenomena": ["Temperatur", "rel. Luftfeuchte", "Luftdruck", "Beleuchtungsstärke", "UV-Intensität", "PM10", "PM2.5"],
    "lastMeasurement": "2018-01-08 12:37:50",
    "lon": 6.623315,
    "lat": 50.905347
  },
  {
    "X_id": "59b3e585d67eb50011239612",
    "createdAt": "2017-09-09 12:58:45",
    "updatedAt": "2018-01-08 12:37:39",
    "name": "Luise trifft Argelander",
    "exposure": "outdoor",
    "model": "homeWifiFeinstaub",
    "description": "Sensebox home WLAN von watterott.com,\n\nSeit 2.11.17 draußen (Balkon, ca. 6m Höhe). \n\nSeit 10.11.17 ca. 18:30 werden beim Feinstaub je 25 Werte in 2s Abstand gemessen und die Mittelwerte übertragen (wenn ich nicht falsch programmiert habe). Die Feinstaubwerte sollten also weniger rauschen.",
    "phenomena": ["Temperatur", "rel. Luftfeuchte", "Luftdruck", "Beleuchtungsstärke", "UV-Intensität", "PM10", "PM2.5"],
    "lastMeasurement": "2018-01-08 12:37:39",
    "lon": 7.098584,
    "lat": 50.721134
  },
  {
    "X_id": "59bec73dd67eb50011dc218c",
    "createdAt": "2017-09-17 19:04:29",
    "updatedAt": "2018-01-08 12:37:53",
    "name": "Box",
    "exposure": "outdoor",
    "model": "homeWifiFeinstaub",
    "phenomena": ["Temperatur", "rel. Luftfeuchte", "Luftdruck", "Beleuchtungsstärke", "UV-Intensität", "PM10", "PM2.5"],
    "lastMeasurement": "2018-01-08 12:37:53",
    "lon": 8.014559,
    "lat": 52.34022
  },
  {
    "X_id": "59c3b5e1d67eb50011335cee",
    "createdAt": "2017-09-21 12:51:45",
    "updatedAt": "2018-01-08 12:37:56",
    "name": "Gruenes_Zentrum",
    "exposure": "outdoor",
    "model": "homeWifiFeinstaub",
    "description": "Auf dem Balkon im 4. Stock, oberhalb der Fußgängerzone (Windthorststr./Bahnhofsvorplatz)",
    "phenomena": ["Temperatur", "rel. Luftfeuchte", "Luftdruck", "Beleuchtungsstärke", "UV-Intensität", "PM10", "PM2.5"],
    "lastMeasurement": "2018-01-08 12:37:56",
    "lon": 7.633289,
    "lat": 51.956907
  },
  {
    "X_id": "59c67b5ed67eb50011666dbb",
    "createdAt": "2017-09-23 15:18:54",
    "updatedAt": "2018-01-08 12:38:22",
    "name": "kartoffelsalat",
    "exposure": "outdoor",
    "model": "homeWifiFeinstaub",
    "description": "sensebox is located on our balcony, fourth floor, facing south(-east). The temperature sensor is beneath the white protecting case on the right hand side.",
    "phenomena": ["Temperatur", "rel. Luftfeuchte", "Luftdruck", "Beleuchtungsstärke", "UV-Intensität", "PM10", "PM2.5"],
    "lastMeasurement": "2018-01-08 12:38:22",
    "lon": 7.62677,
    "lat": 51.946322,
    "weblink": "https://kartoffelsalat.ddns.net"
  },
  {
    "X_id": "59d7de4c66f66a0010797868",
    "createdAt": "2017-10-06 19:49:32",
    "updatedAt": "2018-01-08 12:38:13",
    "name": "Krautspace Jena",
    "exposure": "outdoor",
    "model": "homeWifiFeinstaub",
    "description": "This sensebox is mounted on the outer wall of our Hackerspace. Across the street is a tall and wide building, and our SenseBox is facing a street light at night. It is mounted in an east-west alley where tall buildings on both sides channel the wind.",
    "phenomena": ["Temperatur", "rel. Luftfeuchte", "Luftdruck", "Beleuchtungsstärke", "UV-Intensität", "PM10", "PM2.5"],
    "lastMeasurement": "2018-01-08 12:38:13",
    "lon": 11.582618,
    "lat": 50.929206,
    "weblink": "https://kraut.space/hswiki:misc:sensebox"
  },
  {
    "X_id": "59d8e2df66f66a00108bd920",
    "createdAt": "2017-10-07 14:21:19",
    "updatedAt": "2018-01-08 12:37:59",
    "name": "Wetterstation/Luftdaten",
    "exposure": "outdoor",
    "model": "homeWifiFeinstaub",
    "phenomena": ["Temperatur", "rel. Luftfeuchte", "Luftdruck", "Beleuchtungsstärke", "UV-Intensität", "PM10", "PM2.5"],
    "lastMeasurement": "2018-01-08 12:37:59",
    "lon": 8.409026,
    "lat": 49.927888,
    "height": 95
  },
  {
    "X_id": "59db43f366f66a0010b69f36",
    "createdAt": "2017-10-09 09:40:03",
    "updatedAt": "2018-01-08 12:33:25",
    "name": "RB-test",
    "exposure": "outdoor",
    "model": "homeWifiFeinstaub",
    "description": "Solar powered with LiIon battery backup, 328P based",
    "phenomena": ["Battery", "UV-Radiation", "Intensity", "Temperatur", "Humidity", "Pressure", "Gewicht", "PM10", "PM2.5"],
    "lastMeasurement": "2018-01-08 12:33:25",
    "lon": 8.711557,
    "lat": 50.30206
  },
  {
    "X_id": "59e4f35549f6f800112de030",
    "createdAt": "2017-10-16 17:58:45",
    "updatedAt": "2018-01-08 12:36:11",
    "name": "Illuminati_Giesing",
    "exposure": "outdoor",
    "model": "homeWifiFeinstaub",
    "phenomena": ["PM10", "PM2.5", "Temperatur", "Relative Luftfeuchte"],
    "lastMeasurement": "2018-01-08 12:36:11",
    "lon": 11.579989,
    "lat": 48.104782
  },
  {
    "X_id": "59eb1c1249f6f80011a3ba91",
    "createdAt": "2017-10-21 10:06:10",
    "updatedAt": "2018-01-08 12:36:54",
    "name": "Melaten Köln",
    "exposure": "outdoor",
    "model": "homeWifiFeinstaub",
    "description": "Aachener Straße gegenüber Friedhof Melaten. Stark befahrene Straße. Aufstellort: Fensterbank im 1. Stock.",
    "phenomena": ["Temperatur", "rel. Luftfeuchte", "Luftdruck", "Beleuchtungsstärke", "UV-Intensität", "PM10", "PM2.5"],
    "lastMeasurement": "2018-01-08 12:36:54",
    "lon": 6.918278,
    "lat": 50.936572
  },
  {
    "X_id": "59f0a3ab215fb8000fdbe24d",
    "createdAt": "2017-10-25 14:46:03",
    "updatedAt": "2018-01-08 12:38:21",
    "name": "Davos Wiesen",
    "exposure": "outdoor",
    "model": "homeWifiFeinstaub",
    "description": "SenseBox Davos Wiesen | 1421 mtr",
    "grouptag": "IKG",
    "phenomena": ["Temperatur", "rel. Luftfeuchte", "Luftdruck", "Beleuchtungsstärke", "UV-Intensität", "PM10", "PM2.5"],
    "lastMeasurement": "2018-01-08 12:38:21",
    "lon": 9.711653,
    "lat": 46.703403,
    "weblink": "http://swisspool.net",
    "height": 1421
  },
  {
    "X_id": "5a0587159fd3c200118eaaf6",
    "createdAt": "2017-11-10 11:01:41",
    "updatedAt": "2018-01-08 12:37:17",
    "name": "Münster nachhaltig e.V.",
    "exposure": "outdoor",
    "model": "homeWifiFeinstaub",
    "phenomena": ["Temperatur", "rel. Luftfeuchte", "Luftdruck", "Beleuchtungsstärke", "UV-Intensität", "PM10", "PM2.5"],
    "lastMeasurement": "2018-01-08 12:37:17",
    "lon": 7.624276,
    "lat": 51.955196
  },
  {
    "X_id": "5a072d559fd3c20011ae82ed",
    "createdAt": "2017-11-11 17:03:17",
    "updatedAt": "2018-01-08 12:37:34",
    "name": "Winz/Baak01",
    "exposure": "outdoor",
    "model": "homeWifiFeinstaub",
    "description": "Hattingen/Ruhr Oberwinzerfeld",
    "phenomena": ["Temperatur", "rel. Luftfeuchte", "Luftdruck", "Beleuchtungsstärke", "UV-Intensität", "PM10", "PM2.5"],
    "lastMeasurement": "2018-01-08 12:37:34",
    "lon": 7.166818,
    "lat": 51.409106
  },
  {
    "X_id": "5a09e5f29fd3c20011e3738f",
    "createdAt": "2017-11-13 18:35:30",
    "updatedAt": "2018-01-08 11:15:51",
    "name": "Förderzentrum West - Viersen",
    "exposure": "outdoor",
    "model": "homeWifiFeinstaub",
    "description": "Die Wetterstation des Förderzentrums West am Standort Dülken.",
    "phenomena": ["Temperatur", "rel. Luftfeuchte", "Luftdruck", "Beleuchtungsstärke", "UV-Intensität", "PM10", "PM2.5"],
    "lastMeasurement": "2018-01-08 11:15:51",
    "lon": 6.341603,
    "lat": 51.264092
  },
  {
    "X_id": "5a1e5bc819991f0011ff24e4",
    "createdAt": "2017-11-29 07:03:36",
    "updatedAt": "2018-01-08 12:38:16",
    "name": "Zuerich",
    "exposure": "outdoor",
    "model": "homeWifiFeinstaub",
    "description": "Gsteigstrasse - Zuerich Hoengg",
    "grouptag": "IKG",
    "phenomena": ["Temperatur", "rel. Luftfeuchte", "Luftdruck", "Beleuchtungsstärke", "UV-Intensität", "PM10", "PM2.5"],
    "lastMeasurement": "2018-01-08 12:38:16",
    "lon": 8.503139,
    "lat": 47.403549,
    "height": 465
  },
  {
    "X_id": "5a2bc42e37b7370010246544",
    "createdAt": "2017-12-09 11:08:30",
    "updatedAt": "2018-01-08 12:35:58",
    "name": "Friedrichswalde",
    "exposure": "outdoor",
    "model": "homeWifiFeinstaub",
    "description": "84m ü.NHN, dachgeschützt unter einem Spielturm in 1,8m über den Boden angebracht, ländlicher Raum //\nSensoren: Feinstaubsensor: SDS011, Temperatur- und Luftfeuchtesensor: DHT22",
    "grouptag": "Schorfheide",
    "phenomena": ["Temperatur", "rel. Luftfeuchte", "PM10", "PM2.5"],
    "lastMeasurement": "2018-01-08 12:35:58",
    "lon": 13.706195,
    "lat": 53.021134,
    "height": 84
  },
  {
    "X_id": "5a2e6b9037b73700105ea907",
    "createdAt": "2017-12-11 11:27:12",
    "updatedAt": "2018-01-06 09:52:36",
    "name": "Gefängnisblick",
    "exposure": "outdoor",
    "model": "homeWifiFeinstaub",
    "grouptag": "gartenstr",
    "phenomena": ["Temperatur", "rel. Luftfeuchte", "Luftdruck", "Beleuchtungsstärke", "UV-Intensität", "PM10", "PM2.5"],
    "lastMeasurement": "2018-01-01 03:59:54",
    "lon": 7.633041,
    "lat": 51.968728
  },
  {
    "X_id": "5a414a7cfaf306000fbb6b99",
    "createdAt": "2017-12-25 18:59:08",
    "updatedAt": "2018-01-07 22:48:09",
    "name": "Wittenau",
    "exposure": "outdoor",
    "model": "homeWifiFeinstaub",
    "phenomena": ["Temperatur", "rel. Luftfeuchte", "Luftdruck", "Beleuchtungsstärke", "UV-Intensität", "PM10", "PM2.5"],
    "lastMeasurement": "2018-01-07 22:48:09",
    "lon": 13.314389,
    "lat": 52.596101
  },
  {
    "X_id": "5a454b8adf5df2001aff322e",
    "createdAt": "2017-12-28 19:52:42",
    "updatedAt": "2018-01-08 12:38:19",
    "name": "Obstgarten1",
    "exposure": "outdoor",
    "model": "homeWifiFeinstaub",
    "phenomena": ["Temperatur", "rel. Luftfeuchte", "Luftdruck", "Beleuchtungsstärke", "UV-Intensität", "PM10", "PM2.5"],
    "lastMeasurement": "2018-01-08 12:38:19",
    "lon": 9.49935,
    "lat": 47.802276,
    "height": 600
  }
]
